src/bigquerydave/__init__.py
src/bigquerydave/bqd.py
src/bigquerydave/loadbqdatasets.py
src/bigquerydave/loadbqtabledef.py
src/bigquerydave/loadbqtables.py
src/bigquerydave/loadbuckets.py
src/bigquerydave/loadgcpfolders.py
src/bigquerydave/loadgcpprojectresources.py
src/bigquerydave/loadgcpprojects.py
src/bigquerydave/loadprojadmins.py
src/bigquerydave/showbqdatasets.py
src/bigquerydave/showbqtables.py
src/bigquerydave/showbucket_uniformaccess.py
src/bigquerydave/showbucketacl.py
src/bigquerydave/showbuckets.py
src/bigquerydave/showcost.py
src/bigquerydave/showfolders.py
src/bigquerydave/showgcp.py
src/bigquerydave/showiam.py
src/bigquerydave/showorg.py
src/bigquerydave/showprojectonwer.py
src/bigquerydave/showsample.py
bigquerydave_package-1.0.1.dist-info/METADATA
bigquerydave_package-1.0.1.dist-info/WHEEL
bigquerydave_package-1.0.1.dist-info/licenses/LICENSE
bigquerydave_package-1.0.1.dist-info/RECORD
